xeuclid/__init__.py
xeuclid/anim.py
xeuclid/curves.py
xeuclid/euclid2.py
xeuclid/euclid3.py
xeuclid/graph_parser.py
xeuclid/tikz_draw.py
xeuclid/tikzrc.py
xeuclid/utils/__init__.py
xeuclid/utils/file_edit.py
xeuclid/utils/math.py
xeuclid-1.0.5.dist-info/METADATA
xeuclid-1.0.5.dist-info/WHEEL
xeuclid-1.0.5.dist-info/top_level.txt
xeuclid-1.0.5.dist-info/RECORD
