Metadata-Version: 2.1
Name: xeuclid
Version: 1.0.5
Summary: A python package for analytic geometry
Home-page: https://github.com/MunirZaman/xeuclid
Author: Munir Uz Zaman
Author-email: bijli.begum.bd@gmail.com
License: UNKNOWN
Platform: UNKNOWN
Requires-Python: >=3.8
Requires-Dist: numpy
Requires-Dist: scipy
Requires-Dist: sympy
Requires-Dist: pdf2image
Requires-Dist: Pillow
